.DS_Store
rec/__init__.py
rec/__version__.py
rec/main.py
rec-0.1.1.dist-info/DESCRIPTION.rst
rec-0.1.1.dist-info/METADATA
rec-0.1.1.dist-info/RECORD
rec-0.1.1.dist-info/WHEEL
rec-0.1.1.dist-info/metadata.json
rec-0.1.1.dist-info/top_level.txt
